{
  "neoforge:conditions": [
    {
      "type": "cofh_core:flag_set",
      "flag": "thermal:machine_augments"
    }
  ],
  "type": "minecraft:crafting_shaped",
  "category": "misc",
  "key": {
    "C": {
      "tag": "forge:plates/constantan"
    },
    "G": {
      "tag": "forge:gears/signalum"
    },
    "S": {
      "tag": "forge:plates/silver"
    },
    "X": {
      "item": "thermal:redstone_servo"
    }
  },
  "pattern": [
    "SGS",
    "CXC",
    "SGS"
  ],
  "result": {
    "item": "thermal:machine_cycle_augment"
  }
}