{
  "type": "minecraft:crafting_shapeless",
  "category": "misc",
  "ingredients": [
    [
      {
        "tag": "c:dusts/lead"
      },
      {
        "tag": "c:ingots/lead"
      }
    ],
    [
      {
        "tag": "c:dusts/lead"
      },
      {
        "tag": "c:ingots/lead"
      }
    ],
    [
      {
        "tag": "c:dusts/lead"
      },
      {
        "tag": "c:ingots/lead"
      }
    ],
    {
      "tag": "c:dusts/diamond"
    },
    [
      {
        "tag": "forge:ender_pearls"
      },
      {
        "tag": "c:dusts/ender_pearl"
      }
    ],
    [
      {
        "tag": "forge:ender_pearls"
      },
      {
        "tag": "c:dusts/ender_pearl"
      }
    ],
    {
      "item": "minecraft:fire_charge"
    }
  ],
  "result": {
    "count": 2,
    "item": "thermal:enderium_ingot"
  }
}